[
    {
    "objectID": "markdown#header-3",
    "page": "Markdown",
    "title": "Header 3"
    },
    {
    "objectID": "markdown#there's-a-horizontal-rule-below-this",
    "page": "Markdown",
    "title": "There's a horizontal rule below this"
    },
    {
    "objectID": "markdown#here-is-an-unordered-list",
    "page": "Markdown",
    "title": "Here is an unordered list"
    },
    {
    "objectID": "markdown#and-an-ordered-list",
    "page": "Markdown",
    "title": "And an ordered list"
    },
    {
    "objectID": "markdown#and-a-nested-list",
    "page": "Markdown",
    "title": "And a nested list"
    },
    {
    "objectID": "markdown#image",
    "page": "Markdown",
    "title": "Image"
    },
    {
    "objectID": "markdown#definition-lists",
    "page": "Markdown",
    "title": "Definition lists"
    },
    {
    "objectID": "markdown#code-blocks",
    "page": "Markdown",
    "title": "Code blocks"
    },
]
